tapioca/__init__.py
tapioca/adapters.py
tapioca/exceptions.py
tapioca/serializers.py
tapioca/tapioca.py
tapioca_wrapper-2.3.0.dist-info/LICENSE
tapioca_wrapper-2.3.0.dist-info/METADATA
tapioca_wrapper-2.3.0.dist-info/WHEEL
tapioca_wrapper-2.3.0.dist-info/top_level.txt
tapioca_wrapper-2.3.0.dist-info/RECORD
